COPYING.GPL-2.0.txt
LICENSE.txt
MANIFEST.in
README.txt
setup.py
bin/termine
data/__init__.py
data/archive.wsdl
data/archive.xsd
data/events.xsd
data/groupwise.wsdl
data/methods.xsd
data/types.xsd
docs/__init__.py
docs/termine.txt
termine/__init__.py
termine/filters.py
termine/genericargparse.py
termine/genericlogger.py
termine/gwexceptions.py
termine/gwise.py
termine/views.py
termine.egg-info/PKG-INFO
termine.egg-info/SOURCES.txt
termine.egg-info/dependency_links.txt
termine.egg-info/requires.txt
termine.egg-info/top_level.txt