Metadata-Version: 1.0
Name: termine
Version: 0.1.5
Summary: Access your Groupwise appointments from the commandline.
Home-page: http://bitbucket.org/cfarrell1980/termine/
Author: Ciaran Farrell
Author-email: cfarrell1980@gmail.com
License: MIT and GPL-2.0
Platform: UNKNOWN
